{
    "chunks": [
        {
            "chunk_id": 1,
            "title": "9_Media Queries",
            "start": 0.0,
            "end": 18.0,
            "text": "Next topic we are going to talk about is Media Queries. Media Queries helps our websites to be responsive. When we talk about responsiveness, we have already discussed it briefly. Responsiveness means that nowadays we have different devices available."
        },
        {
            "chunk_id": 2,
            "title": "9_Media Queries",
            "start": 13.0,
            "end": 29.0,
            "text": "Responsiveness means that nowadays we have different devices available. Some have phone sizes, some have iPhones, some have Samsung. Every phone can have a screen size, high, to it, everything is different. In fact, if we talk about phones, their orientation is also different."
        },
        {
            "chunk_id": 3,
            "title": "9_Media Queries",
            "start": 25.0,
            "end": 45.0,
            "text": "In fact, if we talk about phones, their orientation is also different. We can use the same website in landscape mode, we can use it in portrait mode. We can open the same website on computers, on laptops, on big screens. So, the responsiveness of a website, that is, according to the properties of our device,"
        },
        {
            "chunk_id": 4,
            "title": "9_Media Queries",
            "start": 39.0,
            "end": 56.0,
            "text": "So, the responsiveness of a website, that is, according to the properties of our device, it has to be changed so that it can be modified so that our UI looks beautiful, the website looks good, the spacing of the element looks good, everything is well aligned, so responsiveness becomes very important for it."
        },
        {
            "chunk_id": 5,
            "title": "9_Media Queries",
            "start": 52.0,
            "end": 72.0,
            "text": "everything is well aligned, so responsiveness becomes very important for it. In today's date, the websites we build, majority of them are 99.99% All the developers try to be responsive because that is the demand of today's market. For example, if we can take an example of another website, let's suppose we open medium.com"
        },
        {
            "chunk_id": 6,
            "title": "9_Media Queries",
            "start": 67.0,
            "end": 88.0,
            "text": "For example, if we can take an example of another website, let's suppose we open medium.com It is a very popular website, whenever we want to read articles, so if I inspect it, if we decrease its size, then some changes will come in it. For example, if the size of our website will decrease, then the right option will completely be removed."
        },
        {
            "chunk_id": 7,
            "title": "9_Media Queries",
            "start": 81.0,
            "end": 97.0,
            "text": "For example, if the size of our website will decrease, then the right option will completely be removed. That is, if my website looks a little neat and clean on the phone, then I have to remove more options from it. This search bar was even smaller."
        },
        {
            "chunk_id": 8,
            "title": "9_Media Queries",
            "start": 95.0,
            "end": 110.0,
            "text": "This search bar was even smaller. Now, we can do one more thing. We have an option in our inspect, which is device mode, from which we can test our website on different devices."
        },
        {
            "chunk_id": 9,
            "title": "9_Media Queries",
            "start": 105.0,
            "end": 125.0,
            "text": "from which we can test our website on different devices. For example, if I want to test my website on iPhone 12 Pro, then my website will look something like this on the phone. If I want to test Samsung Galaxy S20 Ultra,"
        },
        {
            "chunk_id": 10,
            "title": "9_Media Queries",
            "start": 121.0,
            "end": 138.0,
            "text": "If I want to test Samsung Galaxy S20 Ultra, then it will look something like this. These are my dimensions of the screen, which is basically 412 x 915. If we want, we can see on iPad Air that my website will look something like this on iPad."
        },
        {
            "chunk_id": 11,
            "title": "9_Media Queries",
            "start": 132.0,
            "end": 152.0,
            "text": "If we want, we can see on iPad Air that my website will look something like this on iPad. And on Samsung Galaxy A51, my website will look something like this on the phone. There are many popular devices here. Otherwise, we can change our width and height by our own will."
        },
        {
            "chunk_id": 12,
            "title": "9_Media Queries",
            "start": 148.0,
            "end": 161.0,
            "text": "Otherwise, we can change our width and height by our own will. So, all the websites we are building as a developer, then we can use this device mode to check their responsiveness. This is available on the browsers."
        },
        {
            "chunk_id": 13,
            "title": "9_Media Queries",
            "start": 159.0,
            "end": 168.0,
            "text": "This is available on the browsers. Now, let's talk about media queries. We will take an example to understand media queries. Now, what is media query?"
        },
        {
            "chunk_id": 14,
            "title": "9_Media Queries",
            "start": 166.0,
            "end": 180.0,
            "text": "Now, what is media query? Our device has some particular media features. For example, my device or environment is basically that place, that system, on which we are opening our website."
        },
        {
            "chunk_id": 15,
            "title": "9_Media Queries",
            "start": 177.0,
            "end": 191.0,
            "text": "that system, on which we are opening our website. It has some properties, like it may have some width. It may have some height, it may have some particular orientation of that device."
        },
        {
            "chunk_id": 16,
            "title": "9_Media Queries",
            "start": 187.0,
            "end": 200.0,
            "text": "it may have some particular orientation of that device. Orientation means that you are running it in landscape mode or portrait mode. What is landscape mode? If we talk about this phone,"
        },
        {
            "chunk_id": 17,
            "title": "9_Media Queries",
            "start": 198.0,
            "end": 210.0,
            "text": "If we talk about this phone, then if I see the phone directly, then I have portrait mode to see any website. And on this device, if I see the content in this way, where the width is increased by height, then we call it landscape mode."
        },
        {
            "chunk_id": 18,
            "title": "9_Media Queries",
            "start": 207.0,
            "end": 220.0,
            "text": "where the width is increased by height, then we call it landscape mode. There may be different modes of devices. And according to each mode or different properties, there should be some responsive changes in our website."
        },
        {
            "chunk_id": 19,
            "title": "9_Media Queries",
            "start": 216.0,
            "end": 231.0,
            "text": "there should be some responsive changes in our website. So, the changes according to the properties are called media features. There are not just many different properties that can be manipulated. So, if I search for media features,"
        },
        {
            "chunk_id": 20,
            "title": "9_Media Queries",
            "start": 228.0,
            "end": 245.0,
            "text": "So, if I search for media features, then we have many media features. We have color, dynamic range, grid, device width, display mode, in this way, there are many monochromes, hover, orientation, pointer,"
        },
        {
            "chunk_id": 21,
            "title": "9_Media Queries",
            "start": 241.0,
            "end": 253.0,
            "text": "in this way, there are many monochromes, hover, orientation, pointer, preference color, screen, contrast. There are many different things that we can do on their basis. But the most used one among them is our width."
        },
        {
            "chunk_id": 22,
            "title": "9_Media Queries",
            "start": 249.0,
            "end": 266.0,
            "text": "But the most used one among them is our width. That is, the width of my device is how my website became responsive. We are talking about the width here, we are talking about the width of viewport. Viewport is the visible part for the device."
        },
        {
            "chunk_id": 23,
            "title": "9_Media Queries",
            "start": 263.0,
            "end": 274.0,
            "text": "Viewport is the visible part for the device. But we don't go into that detail. Otherwise, you can go to viewport mdn and read it in detail. Whenever we are talking about CSS, HTML, CSS, JavaScript,"
        },
        {
            "chunk_id": 24,
            "title": "9_Media Queries",
            "start": 271.0,
            "end": 282.0,
            "text": "Whenever we are talking about CSS, HTML, CSS, JavaScript, then we are talking about viewport. We are talking about the viewport of the browser. The part of our web page will be the viewport for us."
        },
        {
            "chunk_id": 25,
            "title": "9_Media Queries",
            "start": 278.0,
            "end": 289.0,
            "text": "The part of our web page will be the viewport for us. We have to ignore it for now. But you can find the viewport in the definitions. So, if I have to take any changes according to the width of the device,"
        },
        {
            "chunk_id": 26,
            "title": "9_Media Queries",
            "start": 286.0,
            "end": 296.0,
            "text": "So, if I have to take any changes according to the width of the device, or any responsiveness, then I will write in my CSS, Adlerate media."
        },
        {
            "chunk_id": 27,
            "title": "9_Media Queries",
            "start": 294.0,
            "end": 302.0,
            "text": "Adlerate media. The start of media query will always be from Adlerate media. And after that, in parenthesis, we will write the name of our media feature,"
        },
        {
            "chunk_id": 28,
            "title": "9_Media Queries",
            "start": 300.0,
            "end": 310.0,
            "text": "we will write the name of our media feature, which feature is responsible for it. Here, the responsiveness is according to the width. If the width is exactly 400 pixels,"
        },
        {
            "chunk_id": 29,
            "title": "9_Media Queries",
            "start": 306.0,
            "end": 316.0,
            "text": "If the width is exactly 400 pixels, then the background color of my div will be red. So, I have written a condition like this. What is the media query?"
        },
        {
            "chunk_id": 30,
            "title": "9_Media Queries",
            "start": 314.0,
            "end": 324.0,
            "text": "What is the media query? If the width of my device is exactly 400 pixels, then any random div of my div, or any heading of h1 color,"
        },
        {
            "chunk_id": 31,
            "title": "9_Media Queries",
            "start": 321.0,
            "end": 331.0,
            "text": "or any heading of h1 color, or font size, we can write multiple queries for div, and then change something for h1."
        },
        {
            "chunk_id": 32,
            "title": "9_Media Queries",
            "start": 329.0,
            "end": 338.0,
            "text": "and then change something for h1. So, these two things will happen. As soon as my width touches 400 pixels. So, in this way, we can define our condition."
        },
        {
            "chunk_id": 33,
            "title": "9_Media Queries",
            "start": 335.0,
            "end": 345.0,
            "text": "So, in this way, we can define our condition. So, let's do this once. We have made a heading h1 in index.html. We can write any random text in it."
        },
        {
            "chunk_id": 34,
            "title": "9_Media Queries",
            "start": 343.0,
            "end": 354.0,
            "text": "We can write any random text in it. And we have given it background color and a border in style.css. So, our page is showing something like this. What we will do is, we will write a media query for it."
        },
        {
            "chunk_id": 35,
            "title": "9_Media Queries",
            "start": 352.0,
            "end": 362.0,
            "text": "What we will do is, we will write a media query for it. Adlerate media. We want that when my device's width is exactly 400 pixels, then what is in that case?"
        },
        {
            "chunk_id": 36,
            "title": "9_Media Queries",
            "start": 360.0,
            "end": 373.0,
            "text": "then what is in that case? In that case, whatever is my h1, for h1, its background color will be red. We will do this safe and refresh."
        },
        {
            "chunk_id": 37,
            "title": "9_Media Queries",
            "start": 370.0,
            "end": 379.0,
            "text": "We will do this safe and refresh. There is no change in refreshing. When will there be a change? There will be a change when my device's width is 400 pixels."
        },
        {
            "chunk_id": 38,
            "title": "9_Media Queries",
            "start": 376.0,
            "end": 387.0,
            "text": "There will be a change when my device's width is 400 pixels. So, I can inspect and change my device's width. Let's remove this first. Now, what is my device's width?"
        },
        {
            "chunk_id": 39,
            "title": "9_Media Queries",
            "start": 385.0,
            "end": 396.0,
            "text": "Now, what is my device's width? When we resize it, I can see the width and height of my device. The width is around 1200 pixels."
        },
        {
            "chunk_id": 40,
            "title": "9_Media Queries",
            "start": 391.0,
            "end": 404.0,
            "text": "The width is around 1200 pixels. So, the width is slowly decreasing. And as we decrease this width, we will make it 400 pixels."
        },
        {
            "chunk_id": 41,
            "title": "9_Media Queries",
            "start": 402.0,
            "end": 410.0,
            "text": "we will make it 400 pixels. So, our change will be exactly 400 pixels. We will increase it a little bit. We will make it 398 pixels."
        },
        {
            "chunk_id": 42,
            "title": "9_Media Queries",
            "start": 409.0,
            "end": 417.0,
            "text": "We will make it 398 pixels. And this blink is 400 pixels. So, exactly 400 pixels. What is my background color change?"
        },
        {
            "chunk_id": 43,
            "title": "9_Media Queries",
            "start": 415.0,
            "end": 423.0,
            "text": "What is my background color change? To red. I want to bring another change here. We want to white our color here."
        },
        {
            "chunk_id": 44,
            "title": "9_Media Queries",
            "start": 420.0,
            "end": 428.0,
            "text": "We want to white our color here. The white combination will look good on red. Refresh. So, this change is exactly 400 pixels."
        },
        {
            "chunk_id": 45,
            "title": "9_Media Queries",
            "start": 426.0,
            "end": 433.0,
            "text": "So, this change is exactly 400 pixels. A little bit of screen size is increased, the change is removed. A little bit of screen size is reduced, the change is removed."
        },
        {
            "chunk_id": 46,
            "title": "9_Media Queries",
            "start": 431.0,
            "end": 442.0,
            "text": "A little bit of screen size is reduced, the change is removed. But exactly 400 pixels if I want a change, then that change can be shown to me in this way. We want to do the same thing for multiple elements."
        },
        {
            "chunk_id": 47,
            "title": "9_Media Queries",
            "start": 439.0,
            "end": 451.0,
            "text": "We want to do the same thing for multiple elements. If I have made a div below, then we want to set the height of this div to 100 pixels."
        },
        {
            "chunk_id": 48,
            "title": "9_Media Queries",
            "start": 450.0,
            "end": 459.0,
            "text": "to 100 pixels. Similarly, we can set the width to 100 pixels. And we will give a background color which is equal to blue. Let's do it safe and refresh."
        },
        {
            "chunk_id": 49,
            "title": "9_Media Queries",
            "start": 457.0,
            "end": 463.0,
            "text": "Let's do it safe and refresh. So, what is this div? I can see it. But as soon as I increased the size,"
        },
        {
            "chunk_id": 50,
            "title": "9_Media Queries",
            "start": 461.0,
            "end": 468.0,
            "text": "But as soon as I increased the size, I can't see the div. Why? Because there is no content in the div."
        },
        {
            "chunk_id": 51,
            "title": "9_Media Queries",
            "start": 465.0,
            "end": 473.0,
            "text": "Because there is no content in the div. And the height and width of the div is set. The background color, whenever the width is 400 pixels,"
        },
        {
            "chunk_id": 52,
            "title": "9_Media Queries",
            "start": 471.0,
            "end": 478.0,
            "text": "whenever the width is 400 pixels, then it is set. That means, that's when the div will be shown. So, if I want to show the div like this,"
        },
        {
            "chunk_id": 53,
            "title": "9_Media Queries",
            "start": 476.0,
            "end": 486.0,
            "text": "So, if I want to show the div like this, then I will have to take exactly 400 pixels to the width of the div. So, in this way, we write our media queries."
        },
        {
            "chunk_id": 54,
            "title": "9_Media Queries",
            "start": 483.0,
            "end": 491.0,
            "text": "So, in this way, we write our media queries. What can we do next? To write our media query, we can also use min, width and max width."
        },
        {
            "chunk_id": 55,
            "title": "9_Media Queries",
            "start": 489.0,
            "end": 499.0,
            "text": "we can also use min, width and max width. In fact, the syntax of exactly this is not used much. But we use min, width and max width a lot."
        },
        {
            "chunk_id": 56,
            "title": "9_Media Queries",
            "start": 496.0,
            "end": 505.0,
            "text": "But we use min, width and max width a lot. For example, the ad-rate media, it means that whatever changes are written inside,"
        },
        {
            "chunk_id": 57,
            "title": "9_Media Queries",
            "start": 502.0,
            "end": 512.0,
            "text": "it means that whatever changes are written inside, it should come when my minimum width is 400 pixels. If the minimum width is 400 pixels or if it is bigger than that,"
        },
        {
            "chunk_id": 58,
            "title": "9_Media Queries",
            "start": 511.0,
            "end": 517.0,
            "text": "or if it is bigger than that, then these changes should come. And the max width means, if my maximum width is 400 pixels,"
        },
        {
            "chunk_id": 59,
            "title": "9_Media Queries",
            "start": 515.0,
            "end": 522.0,
            "text": "if my maximum width is 400 pixels, then these changes should come. If the maximum width is less than that, then these changes should be applied to me."
        },
        {
            "chunk_id": 60,
            "title": "9_Media Queries",
            "start": 520.0,
            "end": 528.0,
            "text": "then these changes should be applied to me. For example, if we want that the maximum width is 400 pixels or if my width is bigger than that,"
        },
        {
            "chunk_id": 61,
            "title": "9_Media Queries",
            "start": 526.0,
            "end": 534.0,
            "text": "or if my width is bigger than that, then my background color should change. In that case, we can write ad-rate media,"
        },
        {
            "chunk_id": 62,
            "title": "9_Media Queries",
            "start": 532.0,
            "end": 545.0,
            "text": "ad-rate media, min width, we can write here 400 pixels. So, if the min width is 400 pixels,"
        },
        {
            "chunk_id": 63,
            "title": "9_Media Queries",
            "start": 542.0,
            "end": 552.0,
            "text": "So, if the min width is 400 pixels, then the background color of my H1 key, we want to do that color, let's suppose green yellow,"
        },
        {
            "chunk_id": 64,
            "title": "9_Media Queries",
            "start": 550.0,
            "end": 557.0,
            "text": "let's suppose green yellow, save and refresh. So, what happened now? By default, my background color is green yellow."
        },
        {
            "chunk_id": 65,
            "title": "9_Media Queries",
            "start": 555.0,
            "end": 563.0,
            "text": "By default, my background color is green yellow. This is because the screen size is bigger than 400 pixels. If we inspect it,"
        },
        {
            "chunk_id": 66,
            "title": "9_Media Queries",
            "start": 561.0,
            "end": 569.0,
            "text": "If we inspect it, and bring something here, so the screen size is 1321, 400 pixels is the minimum width,"
        },
        {
            "chunk_id": 67,
            "title": "9_Media Queries",
            "start": 567.0,
            "end": 575.0,
            "text": "400 pixels is the minimum width, so till then, this line will be green. Slowly, slowly, slowly, then it will touch 400 pixels."
        },
        {
            "chunk_id": 68,
            "title": "9_Media Queries",
            "start": 573.0,
            "end": 581.0,
            "text": "then it will touch 400 pixels. As soon as it touches 400 pixels, the background color will be green. Because I also wrote 400 pixels in this query,"
        },
        {
            "chunk_id": 69,
            "title": "9_Media Queries",
            "start": 579.0,
            "end": 587.0,
            "text": "Because I also wrote 400 pixels in this query, so this query was written in the query, so this query was written in the query, so this query was written in the query,"
        },
        {
            "chunk_id": 70,
            "title": "9_Media Queries",
            "start": 585.0,
            "end": 593.0,
            "text": "so this query was written in the query, and this query was written in the query, so it will override. Override means this query will be implemented,"
        },
        {
            "chunk_id": 71,
            "title": "9_Media Queries",
            "start": 591.0,
            "end": 599.0,
            "text": "Override means this query will be implemented, which we had read in the CSS rules. If I had done exactly 401 here, then it wouldn't have overrided in that case,"
        },
        {
            "chunk_id": 72,
            "title": "9_Media Queries",
            "start": 597.0,
            "end": 605.0,
            "text": "then it wouldn't have overrided in that case, but it would have been ready in that case. But because it is 400, so the background color has overrided,"
        },
        {
            "chunk_id": 73,
            "title": "9_Media Queries",
            "start": 603.0,
            "end": 611.0,
            "text": "so the background color has overrided, so my color is green yellow. And it has reduced a little from 400, so we will return to our original color,"
        },
        {
            "chunk_id": 74,
            "title": "9_Media Queries",
            "start": 609.0,
            "end": 617.0,
            "text": "so we will return to our original color, which means it will be yellow. So, I am going to do this min width in 500 pixels,"
        },
        {
            "chunk_id": 75,
            "title": "9_Media Queries",
            "start": 615.0,
            "end": 623.0,
            "text": "in 500 pixels, or we will do it in 700 pixels. And one is written as a media query,"
        },
        {
            "chunk_id": 76,
            "title": "9_Media Queries",
            "start": 621.0,
            "end": 631.0,
            "text": "as a media query, for my max width. We will do the max width in 200 pixels."
        },
        {
            "chunk_id": 77,
            "title": "9_Media Queries",
            "start": 629.0,
            "end": 637.0,
            "text": "in 200 pixels. On H1, we want, if the maximum width is 200 pixels, or the smallest width is my width,"
        },
        {
            "chunk_id": 78,
            "title": "9_Media Queries",
            "start": 635.0,
            "end": 643.0,
            "text": "or the smallest width is my width, then in that case, we will make the background color pink. Safe, Refresh."
        },
        {
            "chunk_id": 79,
            "title": "9_Media Queries",
            "start": 641.0,
            "end": 649.0,
            "text": "Safe, Refresh. So, let's look at the changes again. Originally, what is my color? My line is green color."
        },
        {
            "chunk_id": 80,
            "title": "9_Media Queries",
            "start": 647.0,
            "end": 655.0,
            "text": "My line is green color. If my minimum width is 700 pixels, or it is bigger than that, then it will be green yellow, or lime color."
        },
        {
            "chunk_id": 81,
            "title": "9_Media Queries",
            "start": 653.0,
            "end": 661.0,
            "text": "then it will be green yellow, or lime color. If we do it in small size, then we will bring it to 700 pixels. This is"
        },
        {
            "chunk_id": 82,
            "title": "9_Media Queries",
            "start": 659.0,
            "end": 667.0,
            "text": "This is 700 pixels. So, it will be green above this, and it will be yellow again."
        },
        {
            "chunk_id": 83,
            "title": "9_Media Queries",
            "start": 665.0,
            "end": 673.0,
            "text": "and it will be yellow again. It will be exactly red and if we go below that, then it will not change."
        },
        {
            "chunk_id": 84,
            "title": "9_Media Queries",
            "start": 671.0,
            "end": 679.0,
            "text": "then it will not change. But as soon as we touch the maximum width, 200 pixels, and in less than that,"
        },
        {
            "chunk_id": 85,
            "title": "9_Media Queries",
            "start": 677.0,
            "end": 685.0,
            "text": "and in less than that, my background color will be converted into pink. So, it will be converted into pink"
        },
        {
            "chunk_id": 86,
            "title": "9_Media Queries",
            "start": 683.0,
            "end": 691.0,
            "text": "So, it will be converted into pink exactly on 200 pixels. And below that, the whole thing will be in pink. In this way, we can bring different changes,"
        },
        {
            "chunk_id": 87,
            "title": "9_Media Queries",
            "start": 689.0,
            "end": 697.0,
            "text": "In this way, we can bring different changes, like our devices are small or big. We are just looking at the background color, but we want, as there are many websites,"
        },
        {
            "chunk_id": 88,
            "title": "9_Media Queries",
            "start": 695.0,
            "end": 703.0,
            "text": "but we want, as there are many websites, the menu is there. We can see the navigation above. But as the website"
        },
        {
            "chunk_id": 89,
            "title": "9_Media Queries",
            "start": 701.0,
            "end": 709.0,
            "text": "above. But as the website is small, a small button or a small option is shown above,"
        },
        {
            "chunk_id": 90,
            "title": "9_Media Queries",
            "start": 707.0,
            "end": 715.0,
            "text": "a small option is shown above, and then the menu is seen. So, we use the more responsiveness in the nav bar."
        },
        {
            "chunk_id": 91,
            "title": "9_Media Queries",
            "start": 713.0,
            "end": 721.0,
            "text": "in the nav bar. So, this is the way to use the maximum width. Apart from this, we can mix multiple things,"
        },
        {
            "chunk_id": 92,
            "title": "9_Media Queries",
            "start": 719.0,
            "end": 727.0,
            "text": "multiple things, multiple dimensions. I can write statements by doing a club like this. So, here we are talking about the"
        },
        {
            "chunk_id": 93,
            "title": "9_Media Queries",
            "start": 725.0,
            "end": 733.0,
            "text": "So, here we are talking about the range of 200 pixels to 300 pixels. So, whenever I want to set the range, we can use"
        },
        {
            "chunk_id": 94,
            "title": "9_Media Queries",
            "start": 731.0,
            "end": 739.0,
            "text": "set the range, we can use min and max. So, let's do this once. I want to write"
        },
        {
            "chunk_id": 95,
            "title": "9_Media Queries",
            "start": 737.0,
            "end": 745.0,
            "text": "I want to write the media, my min width, 200 pixels,"
        },
        {
            "chunk_id": 96,
            "title": "9_Media Queries",
            "start": 743.0,
            "end": 751.0,
            "text": "200 pixels, and max width, 300 pixels."
        },
        {
            "chunk_id": 97,
            "title": "9_Media Queries",
            "start": 749.0,
            "end": 757.0,
            "text": "300 pixels. In between that, the background color of H1, let's suppose"
        },
        {
            "chunk_id": 98,
            "title": "9_Media Queries",
            "start": 755.0,
            "end": 763.0,
            "text": "let's suppose we want to convert that color to long green color green."
        },
        {
            "chunk_id": 99,
            "title": "9_Media Queries",
            "start": 761.0,
            "end": 769.0,
            "text": "long green color green. Let's suppose we want to convert it to magenta. We saved the magenta, and refreshed it. Now, the"
        },
        {
            "chunk_id": 100,
            "title": "9_Media Queries",
            "start": 767.0,
            "end": 775.0,
            "text": "and refreshed it. Now, the line will remain green, but between 200 and 300, the magenta color will come. As soon as we touch 300,"
        },
        {
            "chunk_id": 101,
            "title": "9_Media Queries",
            "start": 773.0,
            "end": 781.0,
            "text": "As soon as we touch 300, as soon as we touch 300, the magenta color will come and it will go up to 200 pixels."
        },
        {
            "chunk_id": 102,
            "title": "9_Media Queries",
            "start": 779.0,
            "end": 787.0,
            "text": "will come and it will go up to 200 pixels. We will convert it to pink by going to 200 pixels. But between 200 and 300,"
        },
        {
            "chunk_id": 103,
            "title": "9_Media Queries",
            "start": 785.0,
            "end": 793.0,
            "text": "But between 200 and 300, we will have magenta background color. So, we can do multiple queries for a range."
        }
    ],
    "full_text": "Next topic we are going to talk about is Media Queries. Media Queries helps our websites to be responsive. When we talk about responsiveness, we have already discussed it briefly. Responsiveness means that nowadays we have different devices available. Some have phone sizes, some have iPhones, some have Samsung. Every phone can have a screen size, high, to it, everything is different. In fact, if we talk about phones, their orientation is also different. We can use the same website in landscape mode, we can use it in portrait mode. We can open the same website on computers, on laptops, on big screens. So, the responsiveness of a website, that is, according to the properties of our device, it has to be changed so that it can be modified so that our UI looks beautiful, the website looks good, the spacing of the element looks good, everything is well aligned, so responsiveness becomes very important for it. In today's date, the websites we build, majority of them are 99.99% All the developers try to be responsive because that is the demand of today's market. For example, if we can take an example of another website, let's suppose we open medium.com It is a very popular website, whenever we want to read articles, so if I inspect it, if we decrease its size, then some changes will come in it. For example, if the size of our website will decrease, then the right option will completely be removed. That is, if my website looks a little neat and clean on the phone, then I have to remove more options from it. This search bar was even smaller. Now, we can do one more thing. We have an option in our inspect, which is device mode, from which we can test our website on different devices. For example, if I want to test my website on iPhone 12 Pro, then my website will look something like this on the phone. If I want to test Samsung Galaxy S20 Ultra, then it will look something like this. These are my dimensions of the screen, which is basically 412 x 915. If we want, we can see on iPad Air that my website will look something like this on iPad. And on Samsung Galaxy A51, my website will look something like this on the phone. There are many popular devices here. Otherwise, we can change our width and height by our own will. So, all the websites we are building as a developer, then we can use this device mode to check their responsiveness. This is available on the browsers. Now, let's talk about media queries. We will take an example to understand media queries. Now, what is media query? Our device has some particular media features. For example, my device or environment is basically that place, that system, on which we are opening our website. It has some properties, like it may have some width. It may have some height, it may have some particular orientation of that device. Orientation means that you are running it in landscape mode or portrait mode. What is landscape mode? If we talk about this phone, then if I see the phone directly, then I have portrait mode to see any website. And on this device, if I see the content in this way, where the width is increased by height, then we call it landscape mode. There may be different modes of devices. And according to each mode or different properties, there should be some responsive changes in our website. So, the changes according to the properties are called media features. There are not just many different properties that can be manipulated. So, if I search for media features, then we have many media features. We have color, dynamic range, grid, device width, display mode, in this way, there are many monochromes, hover, orientation, pointer, preference color, screen, contrast. There are many different things that we can do on their basis. But the most used one among them is our width. That is, the width of my device is how my website became responsive. We are talking about the width here, we are talking about the width of viewport. Viewport is the visible part for the device. But we don't go into that detail. Otherwise, you can go to viewport mdn and read it in detail. Whenever we are talking about CSS, HTML, CSS, JavaScript, then we are talking about viewport. We are talking about the viewport of the browser. The part of our web page will be the viewport for us. We have to ignore it for now. But you can find the viewport in the definitions. So, if I have to take any changes according to the width of the device, or any responsiveness, then I will write in my CSS, Adlerate media. The start of media query will always be from Adlerate media. And after that, in parenthesis, we will write the name of our media feature, which feature is responsible for it. Here, the responsiveness is according to the width. If the width is exactly 400 pixels, then the background color of my div will be red. So, I have written a condition like this. What is the media query? If the width of my device is exactly 400 pixels, then any random div of my div, or any heading of h1 color, or font size, we can write multiple queries for div, and then change something for h1. So, these two things will happen. As soon as my width touches 400 pixels. So, in this way, we can define our condition. So, let's do this once. We have made a heading h1 in index.html. We can write any random text in it. And we have given it background color and a border in style.css. So, our page is showing something like this. What we will do is, we will write a media query for it. Adlerate media. We want that when my device's width is exactly 400 pixels, then what is in that case? In that case, whatever is my h1, for h1, its background color will be red. We will do this safe and refresh. There is no change in refreshing. When will there be a change? There will be a change when my device's width is 400 pixels. So, I can inspect and change my device's width. Let's remove this first. Now, what is my device's width? When we resize it, I can see the width and height of my device. The width is around 1200 pixels. So, the width is slowly decreasing. And as we decrease this width, we will make it 400 pixels. So, our change will be exactly 400 pixels. We will increase it a little bit. We will make it 398 pixels. And this blink is 400 pixels. So, exactly 400 pixels. What is my background color change? To red. I want to bring another change here. We want to white our color here. The white combination will look good on red. Refresh. So, this change is exactly 400 pixels. A little bit of screen size is increased, the change is removed. A little bit of screen size is reduced, the change is removed. But exactly 400 pixels if I want a change, then that change can be shown to me in this way. We want to do the same thing for multiple elements. If I have made a div below, then we want to set the height of this div to 100 pixels. Similarly, we can set the width to 100 pixels. And we will give a background color which is equal to blue. Let's do it safe and refresh. So, what is this div? I can see it. But as soon as I increased the size, I can't see the div. Why? Because there is no content in the div. And the height and width of the div is set. The background color, whenever the width is 400 pixels, then it is set. That means, that's when the div will be shown. So, if I want to show the div like this, then I will have to take exactly 400 pixels to the width of the div. So, in this way, we write our media queries. What can we do next? To write our media query, we can also use min, width and max width. In fact, the syntax of exactly this is not used much. But we use min, width and max width a lot. For example, the ad-rate media, it means that whatever changes are written inside, it should come when my minimum width is 400 pixels. If the minimum width is 400 pixels or if it is bigger than that, then these changes should come. And the max width means, if my maximum width is 400 pixels, then these changes should come. If the maximum width is less than that, then these changes should be applied to me. For example, if we want that the maximum width is 400 pixels or if my width is bigger than that, then my background color should change. In that case, we can write ad-rate media, min width, we can write here 400 pixels. So, if the min width is 400 pixels, then the background color of my H1 key, we want to do that color, let's suppose green yellow, save and refresh. So, what happened now? By default, my background color is green yellow. This is because the screen size is bigger than 400 pixels. If we inspect it, and bring something here, so the screen size is 1321, 400 pixels is the minimum width, so till then, this line will be green. Slowly, slowly, slowly, then it will touch 400 pixels. As soon as it touches 400 pixels, the background color will be green. Because I also wrote 400 pixels in this query, so this query was written in the query, so this query was written in the query, so this query was written in the query, and this query was written in the query, so it will override. Override means this query will be implemented, which we had read in the CSS rules. If I had done exactly 401 here, then it wouldn't have overrided in that case, but it would have been ready in that case. But because it is 400, so the background color has overrided, so my color is green yellow. And it has reduced a little from 400, so we will return to our original color, which means it will be yellow. So, I am going to do this min width in 500 pixels, or we will do it in 700 pixels. And one is written as a media query, for my max width. We will do the max width in 200 pixels. On H1, we want, if the maximum width is 200 pixels, or the smallest width is my width, then in that case, we will make the background color pink. Safe, Refresh. So, let's look at the changes again. Originally, what is my color? My line is green color. If my minimum width is 700 pixels, or it is bigger than that, then it will be green yellow, or lime color. If we do it in small size, then we will bring it to 700 pixels. This is 700 pixels. So, it will be green above this, and it will be yellow again. It will be exactly red and if we go below that, then it will not change. But as soon as we touch the maximum width, 200 pixels, and in less than that, my background color will be converted into pink. So, it will be converted into pink exactly on 200 pixels. And below that, the whole thing will be in pink. In this way, we can bring different changes, like our devices are small or big. We are just looking at the background color, but we want, as there are many websites, the menu is there. We can see the navigation above. But as the website is small, a small button or a small option is shown above, and then the menu is seen. So, we use the more responsiveness in the nav bar. So, this is the way to use the maximum width. Apart from this, we can mix multiple things, multiple dimensions. I can write statements by doing a club like this. So, here we are talking about the range of 200 pixels to 300 pixels. So, whenever I want to set the range, we can use min and max. So, let's do this once. I want to write the media, my min width, 200 pixels, and max width, 300 pixels. In between that, the background color of H1, let's suppose we want to convert that color to long green color green. Let's suppose we want to convert it to magenta. We saved the magenta, and refreshed it. Now, the line will remain green, but between 200 and 300, the magenta color will come. As soon as we touch 300, as soon as we touch 300, the magenta color will come and it will go up to 200 pixels. We will convert it to pink by going to 200 pixels. But between 200 and 300, we will have magenta background color. So, we can do multiple queries for a range."
}